aws_saml_login/__init__.py
aws_saml_login/saml.py
aws_saml_login-1.0.11.dist-info/DESCRIPTION.rst
aws_saml_login-1.0.11.dist-info/METADATA
aws_saml_login-1.0.11.dist-info/RECORD
aws_saml_login-1.0.11.dist-info/WHEEL
aws_saml_login-1.0.11.dist-info/entry_points.txt
aws_saml_login-1.0.11.dist-info/metadata.json
aws_saml_login-1.0.11.dist-info/top_level.txt
