Metadata-Version: 2.0
Name: aws-saml-login
Version: 1.0.11
Summary: SAML login for AWS using Shibboleth IDP
Home-page: https://github.com/zalando/aws-saml-login
Author: Henning Jacobs
Author-email: henning.jacobs@zalando.de
License: Apache License 2.0
Keywords: aws saml federated login shibboleth identity provider sts
Platform: UNKNOWN
Classifier: Development Status :: 4 - Beta
Classifier: Environment :: Console
Classifier: Intended Audience :: Developers
Classifier: Intended Audience :: System Administrators
Classifier: License :: OSI Approved :: Apache Software License
Classifier: Operating System :: POSIX :: Linux
Classifier: Programming Language :: Python
Classifier: Programming Language :: Python :: 3.4
Classifier: Programming Language :: Python :: Implementation :: CPython
Requires-Dist: beautifulsoup4 (>=4.3.2)
Requires-Dist: boto3 (>=1.2.2)
Requires-Dist: requests (>=2.2.1)
